setup.py
tinystats/__init__.py
tinystats/cli.py
tinystats.egg-info/PKG-INFO
tinystats.egg-info/SOURCES.txt
tinystats.egg-info/dependency_links.txt
tinystats.egg-info/entry_points.txt
tinystats.egg-info/not-zip-safe
tinystats.egg-info/requires.txt
tinystats.egg-info/top_level.txt