Metadata-Version: 1.1
Name: tinystats
Version: 0.0.0
Summary: Command-line tool for fetching message, URL, and subscriber data for the TinyLetter newsletters you own.
Home-page: https://github.com/jsvine/tinystats
Author: Jeremy Singer-Vine
Author-email: jsvine@gmail.com
License: MIT
Keywords: tinyletter
Platform: UNKNOWN
Classifier: Development Status :: 3 - Alpha
Classifier: Intended Audience :: Developers
Classifier: License :: OSI Approved :: MIT License
